sup-0.1.1.dist-info/METADATA
sup-0.1.1.dist-info/WHEEL
sup-0.1.1.dist-info/entry_points.txt
sup/__init__.py
sup/__main__.py
sup/_sup.cp313-win32.pyd
sup/bin/rg
sup/bin/rg.exe
sup-0.1.1.dist-info/RECORD
