Metadata-Version: 2.4
Name: sup
Version: 0.1.1
Classifier: Programming Language :: Rust
Classifier: Programming Language :: Python :: Implementation :: CPython
Classifier: Programming Language :: Python :: 3.13
Classifier: Development Status :: 3 - Alpha
Classifier: Intended Audience :: Developers
Classifier: License :: OSI Approved :: MIT License
Classifier: Operating System :: OS Independent
Requires-Dist: pytest>=7.0 ; extra == 'dev'
Requires-Dist: maturin>=1.7 ; extra == 'dev'
Provides-Extra: dev
Summary: A Python package with Rust-based ripgrep implementation
Author-email: Your Name <your.email@example.com>
License: MIT
Requires-Python: >=3.13
